MANIFEST.in
setup.py
claid_designer/.gitignore
claid_designer/LICENSE.txt
claid_designer/NOTICES
claid_designer/README.md
claid_designer/__init__.py
claid_designer/claid_designer.py
claid_designer/config.claid
claid_designer/empty_workshop_config.json
claid_designer/example_config_claid.json
claid_designer/example_config_claid_easy.json
claid_designer/oldCLAID.py
claid_designer/test_designer.py
claid_designer.egg-info/PKG-INFO
claid_designer.egg-info/SOURCES.txt
claid_designer.egg-info/dependency_links.txt
claid_designer.egg-info/requires.txt
claid_designer.egg-info/top_level.txt
claid_designer/__pycache__/claid_designer.cpython-312.pyc
claid_designer/__pycache__/claid_designer.cpython-38.pyc
claid_designer/__pycache__/claid_designer.cpython-39.pyc
claid_designer/config/.gitignore
claid_designer/config/__init__.py
claid_designer/config/channel_description.py
claid_designer/config/config.py
claid_designer/config/__pycache__/__init__.cpython-312.pyc
claid_designer/config/__pycache__/__init__.cpython-39.pyc
claid_designer/config/__pycache__/channel_description.cpython-312.pyc
claid_designer/config/__pycache__/channel_description.cpython-39.pyc
claid_designer/config/__pycache__/config.cpython-312.pyc
claid_designer/config/__pycache__/config.cpython-39.pyc
claid_designer/ui/.gitignore
claid_designer/ui/__init__.py
claid_designer/ui/animated_button.py
claid_designer/ui/channel.py
claid_designer/ui/claid_designer_ui.py
claid_designer/ui/host_graphics_item.py
claid_designer/ui/landing_page.py
claid_designer/ui/log_message_view.py
claid_designer/ui/m_n_test.json
claid_designer/ui/module_catalog.py
claid_designer/ui/module_graphics_item.py
claid_designer/ui/non_scrollable_graphics_view.py
claid_designer/ui/path_graphics_item.py
claid_designer/ui/property_input_dialog.py
claid_designer/ui/style.qss
claid_designer/ui/__pycache__/__init__.cpython-312.pyc
claid_designer/ui/__pycache__/__init__.cpython-38.pyc
claid_designer/ui/__pycache__/__init__.cpython-39.pyc
claid_designer/ui/__pycache__/channel.cpython-312.pyc
claid_designer/ui/__pycache__/channel.cpython-38.pyc
claid_designer/ui/__pycache__/channel.cpython-39.pyc
